ast_transforms/__init__.py
ast_transforms/generate_init.py
ast_transforms/utils.py
ast_transforms/new_utils/__init__.py
ast_transforms/passes/__init__.py
ast_transforms/passes/add_func_decorator.py
ast_transforms/passes/attach_def_use_vars.py
ast_transforms/passes/get_used_names.py
ast_transforms/passes/hoist_shape_attr.py
ast_transforms/passes/remove_func_arg_annotation.py
ast_transforms/passes/remove_func_decorator.py
ast_transforms/passes/replace_name.py
ast_transforms/passes/to_single_op_form.py
ast_transforms/passes/where_to_ternary.py
ast_transforms-0.2.0.dist-info/METADATA
ast_transforms-0.2.0.dist-info/WHEEL
ast_transforms-0.2.0.dist-info/top_level.txt
ast_transforms-0.2.0.dist-info/RECORD
