Metadata-Version: 2.4
Name: ast-transforms
Version: 0.2.0
Summary: A collection of AST-based transformations
Home-page: https://github.com/habanero-lab/ast-transforms
Author: Tong Zhou
Author-email: zt9465@gmail.com
Classifier: Programming Language :: Python :: 3
Classifier: License :: OSI Approved :: MIT License
Classifier: Operating System :: OS Independent
Requires-Python: >=3.9
Requires-Dist: ast_comments
Dynamic: author
Dynamic: author-email
Dynamic: classifier
Dynamic: description
Dynamic: description-content-type
Dynamic: home-page
Dynamic: requires-dist
Dynamic: requires-python
Dynamic: summary
